LICENSE
MANIFEST.in
README.md
setup.py
libpythonpro/__init__.py
libpythonpro/guithub_api.py
libpythonproteste.egg-info/PKG-INFO
libpythonproteste.egg-info/SOURCES.txt
libpythonproteste.egg-info/dependency_links.txt
libpythonproteste.egg-info/not-zip-safe
libpythonproteste.egg-info/requires.txt
libpythonproteste.egg-info/top_level.txt